adal/__init__.py
adal/adal_error.py
adal/argument.py
adal/authentication_context.py
adal/authentication_parameters.py
adal/authority.py
adal/cache_driver.py
adal/code_request.py
adal/constants.py
adal/log.py
adal/mex.py
adal/oauth2_client.py
adal/self_signed_jwt.py
adal/token_cache.py
adal/token_request.py
adal/user_realm.py
adal/util.py
adal/wstrust_request.py
adal/wstrust_response.py
adal/xmlutil.py
adal-1.2.7.dist-info/LICENSE
adal-1.2.7.dist-info/METADATA
adal-1.2.7.dist-info/WHEEL
adal-1.2.7.dist-info/top_level.txt
adal-1.2.7.dist-info/RECORD
