Metadata-Version: 2.1
Name: adal
Version: 1.2.7
Summary: Note: This library is already replaced by MSAL Python, available here: https://pypi.org/project/msal/ .ADAL Python remains available here as a legacy. The ADAL for Python library makes it easy for python application to authenticate to Azure Active Directory (AAD) in order to access AAD protected web resources.
Home-page: https://github.com/AzureAD/azure-activedirectory-library-for-python
Author: Microsoft Corporation
Author-email: nugetaad@microsoft.com
License: MIT
Platform: UNKNOWN
Classifier: Development Status :: 6 - Mature
Classifier: Programming Language :: Python
Classifier: Programming Language :: Python :: 2
Classifier: Programming Language :: Python :: 2.7
Classifier: Programming Language :: Python :: 3
Classifier: Programming Language :: Python :: 3.3
Classifier: Programming Language :: Python :: 3.4
Classifier: Programming Language :: Python :: 3.5
Classifier: Programming Language :: Python :: 3.6
Classifier: License :: OSI Approved :: MIT License
